{
	"schemaVersion": 1,
	"id": "codicraft_rarities",
	"version": "${version}",
	"name": "Rarities",
	"description": "Mod to customize Exclusive Item",
	"authors": [
		"Galysso"
	],
	"contact": {
		"homepage": "https://fabricmc.net/",
		"sources": "https://github.com/FabricMC/fabric-example-mod"
	},
	"license": "CC0-1.0",
	"icon": "assets/modid/icon.png",
	"environment": "*",
	"entrypoints": {
		"main": [
			"galysso.codicraft.exclusive_item_tweaks.ExclusiveItemTweaksMain"
		]
	},
	"mixins": [
      "ExclusiveItemTweaks.mixins.json"
	],
	"depends": {
		"fabricloader": ">=0.16.10",
		"minecraft": "~1.21.1",
		"java": ">=21",
		"fabric-api": "*"
	},
	"suggests": {
		"another-mod": "*"
	}
}